rs3/RuleSet3.pkl
rs3/__init__.py
rs3/_nbdev.py
rs3/predict.py
rs3/predicttarg.py
rs3/seq.py
rs3/target_lite_model.pkl
rs3/target_model.pkl
rs3/targetdata.py
rs3/targetfeat.py
rs3-0.0.18.dist-info/licenses/LICENSE
rs3-0.0.18.dist-info/METADATA
rs3-0.0.18.dist-info/WHEEL
rs3-0.0.18.dist-info/top_level.txt
rs3-0.0.18.dist-info/RECORD
