Metadata-Version: 2.4
Name: rs3
Version: 0.0.18
Summary: Predict the activity of CRISPR sgRNAs
Home-page: https://github.com/gpp-rnd/rs3/tree/master/
Author: Peter Deweirdt
Author-email: petedeweirdt@gmail.com
License: Apache Software License 2.0
Keywords: rs3,CRISPR,sgrna
Classifier: Development Status :: 3 - Alpha
Classifier: Intended Audience :: Developers
Classifier: Natural Language :: English
Classifier: Programming Language :: Python :: 3.7
Classifier: Programming Language :: Python :: 3.8
Classifier: Programming Language :: Python :: 3.9
Classifier: License :: OSI Approved :: Apache Software License
Requires-Python: >=3.7
License-File: LICENSE
Requires-Dist: pip
Requires-Dist: packaging
Requires-Dist: joblib>=1.0.1
Requires-Dist: pandas>=1.0.0
Requires-Dist: lightgbm<=3.3.5,>=3.0.0
Requires-Dist: sglearn>=1.2.5
Requires-Dist: tqdm>=4.61.2
Requires-Dist: pyarrow>=4.0.1
Requires-Dist: biopython>=1.78
Requires-Dist: scikit-learn<=1.0.2,>=0.24.2
Requires-Dist: requests>=2.25.1
Requires-Dist: numpy<=1.26.4
Provides-Extra: dev
Requires-Dist: gpplot>=0.5.0; extra == "dev"
Requires-Dist: seaborn>=0.11.0; extra == "dev"
Requires-Dist: scipy>=1.0.1; extra == "dev"
Requires-Dist: jupyterlab>=3.0.0; extra == "dev"
Requires-Dist: nbdev<2.0.0,>=1.1.14; extra == "dev"
Requires-Dist: matplotlib>=3.3.4; extra == "dev"
Requires-Dist: tabulate>=0.8.9; extra == "dev"
Requires-Dist: jupyter-client<=6.1.12; extra == "dev"
Dynamic: author
Dynamic: author-email
Dynamic: classifier
Dynamic: description
Dynamic: description-content-type
Dynamic: home-page
Dynamic: keywords
Dynamic: license
Dynamic: license-file
Dynamic: provides-extra
Dynamic: requires-dist
Dynamic: requires-python
Dynamic: summary
